apimodel/__init__.py
apimodel/__main__.py
apimodel/apimodel.py
apimodel/errors.py
apimodel/fields.py
apimodel/generator.py
apimodel/localization.py
apimodel/parser.py
apimodel/py.typed
apimodel/tutils.py
apimodel/utility.py
apimodel/validation.py
apimodels-0.0.1.dist-info/METADATA
apimodels-0.0.1.dist-info/WHEEL
apimodels-0.0.1.dist-info/top_level.txt
apimodels-0.0.1.dist-info/RECORD
